dividere/MsgLib_pb2.py
dividere/__init__.py
dividere/connection.py
dividere/messaging.py
dividere/registry.py
dividere/service.py
dividere-2.2.0.dist-info/LICENSE
dividere-2.2.0.dist-info/METADATA
dividere-2.2.0.dist-info/WHEEL
dividere-2.2.0.dist-info/top_level.txt
dividere-2.2.0.dist-info/RECORD
