Metadata-Version: 2.1
Name: dividere
Version: 2.2.0
Summary: Distributed Systems Framework
Author: Grant Lipelt
Author-email: <lipeltgm@gmail.com>
Keywords: python,ZeroMq,zmq,0mq,protobuf
Classifier: Development Status :: 1 - Planning
Classifier: Intended Audience :: Developers
Classifier: Programming Language :: Python :: 3
Classifier: Operating System :: Unix
License-File: LICENSE
Requires-Dist: zmq
Requires-Dist: protobuf (>=3.19.0)
